_pytest/__init__.py
_pytest/_argcomplete.py
_pytest/_version.py
_pytest/cacheprovider.py
_pytest/capture.py
_pytest/compat.py
_pytest/debugging.py
_pytest/deprecated.py
_pytest/doctest.py
_pytest/faulthandler.py
_pytest/fixtures.py
_pytest/freeze_support.py
_pytest/helpconfig.py
_pytest/hookspec.py
_pytest/junitxml.py
_pytest/legacypath.py
_pytest/logging.py
_pytest/main.py
_pytest/monkeypatch.py
_pytest/nodes.py
_pytest/nose.py
_pytest/outcomes.py
_pytest/pastebin.py
_pytest/pathlib.py
_pytest/pytester.py
_pytest/pytester_assertions.py
_pytest/python.py
_pytest/python_api.py
_pytest/python_path.py
_pytest/recwarn.py
_pytest/reports.py
_pytest/runner.py
_pytest/scope.py
_pytest/setuponly.py
_pytest/setupplan.py
_pytest/skipping.py
_pytest/stash.py
_pytest/stepwise.py
_pytest/terminal.py
_pytest/threadexception.py
_pytest/timing.py
_pytest/tmpdir.py
_pytest/unittest.py
_pytest/unraisableexception.py
_pytest/warning_types.py
_pytest/warnings.py
_pytest/_code/__init__.py
_pytest/_code/code.py
_pytest/_code/source.py
_pytest/_io/__init__.py
_pytest/_io/saferepr.py
_pytest/_io/terminalwriter.py
_pytest/_io/wcwidth.py
_pytest/assertion/__init__.py
_pytest/assertion/rewrite.py
_pytest/assertion/truncate.py
_pytest/assertion/util.py
_pytest/config/__init__.py
_pytest/config/argparsing.py
_pytest/config/compat.py
_pytest/config/exceptions.py
_pytest/config/findpaths.py
_pytest/mark/__init__.py
_pytest/mark/expression.py
_pytest/mark/structures.py
atomicwrites/__init__.py
attr/__init__.py
attr/_cmp.py
attr/_compat.py
attr/_config.py
attr/_funcs.py
attr/_make.py
attr/_next_gen.py
attr/_version_info.py
attr/converters.py
attr/exceptions.py
attr/filters.py
attr/setters.py
attr/validators.py
attrs/__init__.py
attrs/converters.py
attrs/exceptions.py
attrs/filters.py
attrs/setters.py
attrs/validators.py
colorama/__init__.py
colorama/ansi.py
colorama/ansitowin32.py
colorama/initialise.py
colorama/win32.py
colorama/winterm.py
cookiecutter/__init__.py
cookiecutter/__main__.py
ifly_uiautotest-0.0.10.dist-info/LICENSE
ifly_uiautotest-0.0.10.dist-info/METADATA
ifly_uiautotest-0.0.10.dist-info/WHEEL
ifly_uiautotest-0.0.10.dist-info/entry_points.txt
ifly_uiautotest-0.0.10.dist-info/top_level.txt
ifly_uiautotest-0.0.10.dist-info/RECORD
