Metadata-Version: 2.1
Name: ifly-uiautotest
Version: 0.0.10
Summary: A small example package
Home-page: 
Author: 
Author-email: 
Classifier: Programming Language :: Python :: 3
Classifier: License :: OSI Approved :: MIT License
Classifier: Operating System :: OS Independent
License-File: LICENSE
Requires-Dist: airtest (==1.2.6)
Requires-Dist: pyppeteer (==0.2.6)
Requires-Dist: artifactory (==0.1.17)
Requires-Dist: pixelmatch
Requires-Dist: paramiko (==2.11.0)
Requires-Dist: pandas (==1.1.5)
Requires-Dist: poco (==0.99.1)
Requires-Dist: pocoui (==1.0.89)
Requires-Dist: allure-combine (==1.0.6)
Requires-Dist: allure-pytest (==2.9.45)
Requires-Dist: allure-python-commons (==2.9.45)
Requires-Dist: openpyxl (==3.0.10)
Requires-Dist: pytest-ordering (==0.6)
Requires-Dist: pytest-repeat (==0.9.1)
Requires-Dist: numpy (==1.21.6)
Requires-Dist: opencv-contrib-python
Requires-Dist: Levenshtein
Requires-Dist: onnxruntime
Requires-Dist: pyclipper
Requires-Dist: requests
Requires-Dist: Shapely (==1.7.1)
Requires-Dist: tqdm
Requires-Dist: addict
